dytranscoder
