Metadata-Version: 1.0
Name: dytranscoder
Version: 0.0.3
Summary: Da yang transcoder Python SDK
Home-page: http://git.hoge.cn/jeffkit/dytranscoder-py
Author: jeff kit
Author-email: jeffkit@hoge.cn
License: UNKNOWN
Platform: UNKNOWN
